odoo/addons/project_task_show_project_manager/README.rst
odoo/addons/project_task_show_project_manager/__init__.py
odoo/addons/project_task_show_project_manager/__manifest__.py
odoo/addons/project_task_show_project_manager/i18n/es.po
odoo/addons/project_task_show_project_manager/models/__init__.py
odoo/addons/project_task_show_project_manager/models/project_task.py
odoo/addons/project_task_show_project_manager/readme/CONFIGURE.md
odoo/addons/project_task_show_project_manager/readme/CONTRIBUTORS.md
odoo/addons/project_task_show_project_manager/readme/DESCRIPTION.md
odoo/addons/project_task_show_project_manager/static/description/icon.png
odoo/addons/project_task_show_project_manager/static/description/index.html
odoo/addons/project_task_show_project_manager/views/project_task_views.xml
odoo_addon_project_task_show_project_manager-18.0.1.0.0.1.dist-info/METADATA
odoo_addon_project_task_show_project_manager-18.0.1.0.0.1.dist-info/WHEEL
odoo_addon_project_task_show_project_manager-18.0.1.0.0.1.dist-info/top_level.txt
odoo_addon_project_task_show_project_manager-18.0.1.0.0.1.dist-info/RECORD
