Metadata-Version: 2.1
Name: odoo-addon-project_task_show_project_manager
Version: 18.0.1.0.0.1
Requires-Python: >=3.10
Requires-Dist: odoo==18.0.*
Summary: Show Project Manager in Project Task
Home-page: https://github.com/sygel-technology/sy-project
License: AGPL-3
Author: Sygel, Odoo Community Association (OCA)
Author-email: support@odoo-community.org
Classifier: Programming Language :: Python
Classifier: Framework :: Odoo
Classifier: Framework :: Odoo :: 18.0
Classifier: License :: OSI Approved :: GNU Affero General Public License v3
